mutil/__init__.py
mutil/cli.py
mutil/util.py
mutil/version.py
mosaicml_mutil-0.0.7.dist-info/METADATA
mosaicml_mutil-0.0.7.dist-info/WHEEL
mosaicml_mutil-0.0.7.dist-info/entry_points.txt
mosaicml_mutil-0.0.7.dist-info/top_level.txt
mosaicml_mutil-0.0.7.dist-info/RECORD
