Metadata-Version: 2.1
Name: mosaicml-mutil
Version: 0.0.7
Summary: Util for stuff
Home-page: https://github.com/mosaicml/mutil
Author: MosaicML
Author-email: team@mosaicml.com
Classifier: Programming Language :: Python :: 3
Classifier: Programming Language :: Python :: 3.8
Classifier: Programming Language :: Python :: 3.9
Requires-Python: >=3.8
Provides-Extra: all
